doorstop/__init__.py
doorstop/cli/__init__.py
doorstop/cli/commands.py
doorstop/cli/main.py
doorstop/cli/tests/__init__.py
doorstop/cli/tests/docs/.doorstop.yml
doorstop/cli/tests/docs/HLT001.yml
doorstop/cli/tests/docs/HLT002.yml
doorstop/cli/tests/docs/HLT003.yml
doorstop/cli/tests/docs/HLT004.yml
doorstop/cli/tests/docs/HLT005.yml
doorstop/cli/tests/files/A001.txt
doorstop/cli/tests/files/A002.txt
doorstop/cli/tests/files/B001.txt
doorstop/cli/tests/files/B002.txt
doorstop/cli/tests/files/C001.txt
doorstop/cli/tests/files/C002.txt
doorstop/cli/tests/files/C003.txt
doorstop/cli/tests/files/exported-map.csv
doorstop/cli/tests/files/exported.csv
doorstop/cli/tests/files/exported.tsv
doorstop/cli/tests/files/exported.xlsx
doorstop/cli/tests/files/template.yml
doorstop/cli/tests/test_all.py
doorstop/cli/tests/test_main.py
doorstop/cli/tests/test_utilities.py
doorstop/cli/tests/tutorial.py
doorstop/cli/utilities.py
doorstop/common.py
doorstop/core/__init__.py
doorstop/core/base.py
doorstop/core/builder.py
doorstop/core/document.py
doorstop/core/editor.py
doorstop/core/exporter.py
doorstop/core/files/assets/doorstop/bootstrap.min.css
doorstop/core/files/assets/doorstop/bootstrap.min.js
doorstop/core/files/assets/doorstop/general.css
doorstop/core/files/assets/doorstop/jquery.min.js
doorstop/core/files/assets/doorstop/sidebar.css
doorstop/core/files/doorstop.css
doorstop/core/files/template.html
doorstop/core/importer.py
doorstop/core/item.py
doorstop/core/publisher.py
doorstop/core/reference_finder.py
doorstop/core/tests/__init__.py
doorstop/core/tests/docs/.doorstop.yml
doorstop/core/tests/docs/LLT001.yml
doorstop/core/tests/docs/LLT002.yml
doorstop/core/tests/docs/LLT003.yml
doorstop/core/tests/docs/LLT004.yml
doorstop/core/tests/docs/LLT005.yml
doorstop/core/tests/docs/LLT007.yml
doorstop/core/tests/docs/LLT008.yml
doorstop/core/tests/docs/LLT009.yml
doorstop/core/tests/docs/LLT010.yml
doorstop/core/tests/files/.doorstop.skip
doorstop/core/tests/files/.doorstop.yml
doorstoph-2.3.dist-info/entry_points.txt
doorstoph-2.3.dist-info/LICENSE.md
doorstoph-2.3.dist-info/WHEEL
doorstoph-2.3.dist-info/METADATA
doorstoph-2.3.dist-info/RECORD
