Metadata-Version: 2.1
Name: doorstoph
Version: 2.3
Summary: Requirements management using version control.
Home-page: https://pypi.org/project/Doorstop
License: LGPLv3
Keywords: requirements-management,version-control,documentation,traceability,markdown,certification,html
Author: Jace Browning
Author-email: jacebrowning@gmail.com
Requires-Python: >=3.6,<4.0
Classifier: Development Status :: 5 - Production/Stable
Classifier: Environment :: Console
Classifier: License :: OSI Approved :: GNU Lesser General Public License v3 (LGPLv3)
Classifier: License :: Other/Proprietary License
Classifier: Operating System :: OS Independent
Classifier: Programming Language :: Python
Classifier: Programming Language :: Python :: 3
Classifier: Programming Language :: Python :: 3.6
Classifier: Programming Language :: Python :: 3.7
Classifier: Programming Language :: Python :: 3.8
Classifier: Programming Language :: Python :: 3.9
Classifier: Topic :: Software Development :: Documentation
Classifier: Topic :: Text Editors :: Documentation
Classifier: Topic :: Text Processing :: Markup
Requires-Dist: Markdown (>=3.3.3,<4.0.0)
Requires-Dist: PyYAML (>=5.1,<6.0)
Requires-Dist: bottle (>=0.12.13,<0.13.0)
Requires-Dist: openpyxl (>=2.6,<3.0)
Requires-Dist: plantuml-markdown (>=3.4.2,<4.0.0)
Requires-Dist: python-markdown-math (>=0.6,<0.7)
Requires-Dist: requests (>=2.0,<3.0)
Project-URL: Documentation, https://doorstop.readthedocs.io
Project-URL: Repository, https://github.com/doorstop-dev/doorstop
